fake_super/README.md
fake_super/__init__.py
fake_super-0.2.1.dist-info/LICENSE.md
fake_super-0.2.1.dist-info/METADATA
fake_super-0.2.1.dist-info/WHEEL
fake_super-0.2.1.dist-info/entry_points.txt
fake_super-0.2.1.dist-info/top_level.txt
fake_super-0.2.1.dist-info/zip-safe
fake_super-0.2.1.dist-info/RECORD
