Metadata-Version: 2.1
Name: fake-super
Version: 0.2.1
Summary: Inspect/apply information created by `rsync --fake-super`
Home-page: https://netfuture.ch/tools/fake-super/
Author: Marcel Waldvogel
Author-email: marcel.waldvogel@trifence.ch
License: MIT
Project-URL: GitLab, https://gitlab.com/MarcelWaldvogel/fake-super/
Project-URL: GitHub, https://github.com/MarcelWaldvogel/fake-super/
Platform: UNKNOWN
Classifier: Development Status :: 3 - Alpha
Classifier: Environment :: Console
Classifier: Intended Audience :: Information Technology
Classifier: Programming Language :: Python :: 3
Classifier: License :: OSI Approved :: MIT License
Classifier: Operating System :: OS Independent
Classifier: Natural Language :: English
Classifier: Topic :: Utilities
Classifier: Topic :: System :: Archiving :: Backup
Classifier: Topic :: System :: Archiving :: Mirroring
Requires-Python: >=3.6
License-File: LICENSE.md
Requires-Dist: setuptools
Requires-Dist: importlib-metadata
